<?xml version="1.0" encoding="Windows-1252"?>
<ItemDB xmlns:xsi="http://www.w3.org/2001/XMLSchema-instance" xmlns:xsd="http://www.w3.org/2001/XMLSchema">
  <nodes>
    <node>
      <name> Ted </name>
      <ID>1</ID>
      <Data>Data</Data>
      <loc>
        <x>-4.13593864</x>
        <y>6.89981461</y>
        <z>4.408498</z>
      </loc>
    </node>
    <node>
      <name> Marshall </name>
      <ID>1</ID>
      <Data>Data</Data>
      <loc>
        <x>5.95634651</x>
        <y>5.68487644</y>
        <z>-0.818277359</z>
      </loc>
    </node>
    <node>
      <name> Lily </name>
      <ID>1</ID>
      <Data>Data</Data>
      <loc>
        <x>1.953455</x>
        <y>7.59451628</y>
        <z>-4.880103</z>
      </loc>
    </node>
    <node>
      <name> Barney </name>
      <ID>1</ID>
      <Data>Data</Data>
      <loc>
        <x>-3.977171</x>
        <y>6.09605026</y>
        <z>-9.141733</z>
      </loc>
    </node>
    <node>
      <name> Robin </name>
      <ID>1</ID>
      <Data>Data</Data>
      <loc>
        <x>5.645096</x>
        <y>6.600594</y>
        <z>5.14645767</z>
      </loc>
    </node>
    <node>
      <name>Van</name>
      <ID>1</ID>
      <Data>Data</Data>
      <loc>
        <x>-2.40671539</x>
        <y>-5.0421257</y>
        <z>2.00069523</z>
      </loc>
    </node>
    <node>
      <name>Claudette</name>
      <ID>1</ID>
      <Data>Data</Data>
      <loc>
        <x>-9.629948</x>
        <y>-1.34676552</y>
        <z>-1.24642944</z>
      </loc>
    </node>
    <node>
      <name>Youko</name>
      <ID>1</ID>
      <Data>Data</Data>
      <loc>
        <x>1.82516563</x>
        <y>0.3876598</y>
        <z>-3.85343266</z>
      </loc>
    </node>
  </nodes>
</ItemDB>